{
    "bookchapter": "ישעיהו",
    "chapter": "סו",
    "versechapter": "יט",
    "bookseder": "ישעיהו",
    "seder": "כו",
    "verseseder": "לו",
    "versenikud": "וְשַׂמְתִּ֨י בָהֶ֜ם א֗וֹת וְשִׁלַּחְתִּ֣י מֵהֶ֣ם ׀ פְּ֠לֵיטִים אֶֽל־ הַגּוֹיִ֞ם תַּרְשִׁ֨ישׁ פּ֥וּל וְל֛וּד מֹ֥שְׁכֵי קֶ֖שֶׁת תֻּבַ֣ל וְיָוָ֑ן הָאִיִּ֣ים הָרְחֹקִ֗ים אֲשֶׁ֨ר לֹא־ שָׁמְע֤וּ אֶת־ שִׁמְעִי֙ וְלֹא־ רָא֣וּ אֶת־ כְּבוֹדִ֔י וְהִגִּ֥ידוּ אֶת־ כְּבוֹדִ֖י בַּגּוֹיִֽם׃ ",
    "versenonikud": "ושמתי בהם אות ושלחתי מהם  פליטים אל הגוים תרשיש פול ולוד משכי קשת תבל ויון האיים הרחקים אשר לא שמעו את שמעי ולא ראו את כבודי והגידו את כבודי בגוים "
}